<?xml version="1.0" encoding="utf-8" ?>
<dwsync>
<file name="box.php" local="128189988600000000" remote="128189988600000000" testing="128189988600000000" />
<file name="currencies.php" local="128189988600000000" remote="128189988600000000" testing="128189988600000000" />
<file name="email.php" local="128189988600000000" remote="128189988600000000" testing="128189988600000000" />
<file name="language.php" local="128189988600000000" remote="128189988600000000" testing="128189988600000000" />
<file name="logger.php" local="128189988600000000" remote="128189988600000000" testing="128189988600000000" />
<file name="message_stack.php" local="128189988600000000" remote="128189988600000000" testing="128189988600000000" />
<file name="mime.php" local="128189988600000000" remote="128189988600000000" testing="128189988600000000" />
<file name="object_info.php" local="128189988600000000" remote="128189988600000000" testing="128189988600000000" />
<file name="order.php" local="128189988600000000" remote="128189988600000000" testing="128189988600000000" />
<file name="payment_module_info.php" local="128189988600000000" remote="128189988600000000" testing="128189988600000000" />
<file name="phplot.php" local="128189988600000000" remote="128189988600000000" testing="128189988600000000" />
<file name="sales_report.php" local="128189988600000000" remote="128189988600000000" testing="128189988600000000" />
<file name="sessions.php" local="128189988600000000" remote="128189988600000000" testing="128189988600000000" />
<file name="shopping_cart.php" local="128189988600000000" remote="128189988600000000" testing="128189988600000000" />
<file name="split_page_results.php" local="128189988600000000" remote="128189988600000000" testing="128189988600000000" />
<file name="table_block.php" local="128189988600000000" remote="128189988600000000" testing="128189988600000000" />
<file name="upload.php" local="128189988600000000" remote="128189988600000000" testing="128189988600000000" />
</dwsync>